[{"name": "\u8f6f\u4ef6", "value": 422}, {"name": "IT\u8fd0\u7ef4", "value": 185}, {"name": "Java", "value": 147}, {"name": "\u524d\u7aef", "value": 144}, {"name": "\u7b97\u6cd5", "value": 138}, {"name": "\u4e91\u8ba1\u7b97/\u5927\u6570\u636e", "value": 129}, {"name": "C/C++", "value": 124}, {"name": "\u6d4b\u8bd5", "value": 124}, {"name": "\u6570\u636e\u6316\u6398", "value": 108}, {"name": "\u6570\u636e\u5e93", "value": 101}, {"name": "PHP", "value": 95}, {"name": "Android", "value": 77}, {"name": "Python", "value": 63}, {"name": "IOS", "value": 63}, {"name": "Node.js", "value": 11}]